gingerit/__init__.py
gingerit/gingerit.py
gingerit-0.8.2.dist-info/LICENSE
gingerit-0.8.2.dist-info/WHEEL
gingerit-0.8.2.dist-info/METADATA
gingerit-0.8.2.dist-info/RECORD
