Metadata-Version: 2.1
Name: gingerit
Version: 0.8.2
Summary: Correcting spelling and grammar mistakes based on the context of complete entences. Wrapper around the gingersoftware.com API
Home-page: https://github.com/Azd325/gingerit
License: MIT
Author: Tim Kleinschmdit
Author-email: tim.kleinschmidt@gmail.com
Requires-Python: >=3.6.2,<4
Classifier: Development Status :: 4 - Beta
Classifier: Environment :: Console
Classifier: Intended Audience :: Developers
Classifier: License :: OSI Approved :: MIT License
Classifier: Operating System :: OS Independent
Classifier: Programming Language :: Python :: 3
Classifier: Programming Language :: Python :: 3.7
Classifier: Programming Language :: Python :: 3.8
Classifier: Programming Language :: Python :: 3.9
Requires-Dist: requests (>=2.25.1,<3.0.0)
